adafruit_lis331.py
adafruit_circuitpython_lis331-1.0.23.dist-info/licenses/LICENSE
adafruit_circuitpython_lis331-1.0.23.dist-info/METADATA
adafruit_circuitpython_lis331-1.0.23.dist-info/WHEEL
adafruit_circuitpython_lis331-1.0.23.dist-info/top_level.txt
adafruit_circuitpython_lis331-1.0.23.dist-info/RECORD
