Metadata-Version: 2.4
Name: adafruit-circuitpython-lis331
Version: 1.0.23
Summary: A library for the ST LIS331 family of high-g 3-axis accelerometers
Author-email: Adafruit Industries <circuitpython@adafruit.com>
License: MIT
Project-URL: Homepage, https://github.com/adafruit/Adafruit_CircuitPython_LIS331
Keywords: adafruit,blinka,circuitpython,micropython,lis331,lis331hh,h3lis331dl,accelerometer,accel,IMU
Classifier: Intended Audience :: Developers
Classifier: Topic :: Software Development :: Libraries
Classifier: Topic :: Software Development :: Embedded Systems
Classifier: Topic :: System :: Hardware
Classifier: License :: OSI Approved :: MIT License
Classifier: Programming Language :: Python :: 3
License-File: LICENSE
Requires-Dist: Adafruit-Blinka
Requires-Dist: adafruit-circuitpython-register
Requires-Dist: adafruit-circuitpython-busdevice
Provides-Extra: optional
Dynamic: license-file
